{
  "clientid": "Seattle Coffee Gear",
  "image": "https://cf6bd535.ngrok.io/devimagestore/site/staples.png",
	"image-link": "http://seattlecoffeegear.com",
	"promotion-image": "",
	"promotion-image-link": "",
	"greeting": "Hi, <g:message code='email.reviewSolicitation.vc.greeting' args='${[firstName]}'/>",
	"greeting2": "Please share your experience.",
	"greeting3": "It will help other shoppers and we'll use it to improve our products.",
	"product-image": "http://se-store.turntodev.com/media/catalog/product/m/s/msj006t.jpg",
	"product-title": "Plaid Cotton Shirt",
	"product-brand": "",
	"photo-teaser": "How did it look in real life?",
	"photo-button": "SHARE A PHOTO"
  "squadName" : "Super hero squad",
  "homeTown" : "Metro City",
  "formed" : 2016,
  "secretBase" : "Super tower",
  "active" : true,
  "members" : [
    {
      "name" : "Molecule Man",
      "age" : 29,
      "secretIdentity" : "Dan Jukes",
      "powers" : [
        "Radiation resistance",
        "Turning tiny",
        "Radiation blast"
      ]
    },
    {
      "name" : "Madame Uppercut",
      "age" : 39,
      "secretIdentity" : "Jane Wilson",
      "powers" : [
        "Million tonne punch",
        "Damage resistance",
        "Superhuman reflexes"
      ]
    },
    {
      "name" : "Eternal Flame",
      "age" : 1000000,
      "secretIdentity" : "Unknown",
      "powers" : [
        "Immortality",
        "Heat Immunity",
        "Inferno",
        "Teleportation",
        "Interdimensional travel"
      ]
    }
  ]
}
